lb_dev_formatting/__init__.py
lb_dev_formatting/constants.py
lb_dev_formatting/commands/__init__.py
lb_dev_formatting/commands/format.py
lb_dev_formatting/data/__init__.py
lb_dev_formatting/data/default.clang-format
lb_dev_formatting/exceptions/__init__.py
lb_dev_formatting/exceptions/command_not_found.py
lb_dev_formatting/exceptions/illegal_argument.py
lb_dev_formatting/formatter/__init__.py
lb_dev_formatting/formatter/c_formatter.py
lb_dev_formatting/formatter/formatter_facade.py
lb_dev_formatting/formatter/python_formatter.py
lb_dev_formatting/hooks/__init__.py
lb_dev_formatting/hooks/format.py
lb_dev_formatting-0.0.7.dist-info/LICENSE
lb_dev_formatting-0.0.7.dist-info/METADATA
lb_dev_formatting-0.0.7.dist-info/WHEEL
lb_dev_formatting-0.0.7.dist-info/entry_points.txt
lb_dev_formatting-0.0.7.dist-info/top_level.txt
lb_dev_formatting-0.0.7.dist-info/RECORD
